{
  "id": "6bd09caf-8195-449d-9317-7b50b2dedf23",
  "prevId": "00000000-0000-0000-0000-000000000000",
  "version": "7",
  "dialect": "postgresql",
  "tables": {
    "public.chapters": {
      "name": "chapters",
      "schema": "",
      "columns": {
        "id": {
          "name": "id",
          "type": "integer",
          "primaryKey": true,
          "notNull": true,
          "identity": {
            "type": "byDefault",
            "name": "chapters_id_seq",
            "schema": "public",
            "increment": "1",
            "startWith": "1",
            "minValue": "1",
            "maxValue": "2147483647",
            "cache": "1",
            "cycle": false
          }
        },
        "chapterNumber": {
          "name": "chapterNumber",
          "type": "integer",
          "primaryKey": false,
          "notNull": true
        },
        "titleEn": {
          "name": "titleEn",
          "type": "varchar(255)",
          "primaryKey": false,
          "notNull": true
        },
        "titleFr": {
          "name": "titleFr",
          "type": "varchar(255)",
          "primaryKey": false,
          "notNull": true
        },
        "descriptionEn": {
          "name": "descriptionEn",
          "type": "text",
          "primaryKey": false,
          "notNull": false
        },
        "descriptionFr": {
          "name": "descriptionFr",
          "type": "text",
          "primaryKey": false,
          "notNull": false
        },
        "contentEn": {
          "name": "contentEn",
          "type": "text",
          "primaryKey": false,
          "notNull": false
        },
        "contentFr": {
          "name": "contentFr",
          "type": "text",
          "primaryKey": false,
          "notNull": false
        },
        "order": {
          "name": "order",
          "type": "integer",
          "primaryKey": false,
          "notNull": true
        },
        "createdAt": {
          "name": "createdAt",
          "type": "timestamp",
          "primaryKey": false,
          "notNull": true,
          "default": "now()"
        },
        "updatedAt": {
          "name": "updatedAt",
          "type": "timestamp",
          "primaryKey": false,
          "notNull": true,
          "default": "now()"
        }
      },
      "indexes": {},
      "foreignKeys": {},
      "compositePrimaryKeys": {},
      "uniqueConstraints": {
        "chapters_chapterNumber_unique": {
          "name": "chapters_chapterNumber_unique",
          "nullsNotDistinct": false,
          "columns": ["chapterNumber"]
        }
      },
      "policies": {},
      "checkConstraints": {},
      "isRLSEnabled": false
    },
    "public.commands": {
      "name": "commands",
      "schema": "",
      "columns": {
        "id": {
          "name": "id",
          "type": "integer",
          "primaryKey": true,
          "notNull": true,
          "identity": {
            "type": "byDefault",
            "name": "commands_id_seq",
            "schema": "public",
            "increment": "1",
            "startWith": "1",
            "minValue": "1",
            "maxValue": "2147483647",
            "cache": "1",
            "cycle": false
          }
        },
        "nameEn": {
          "name": "nameEn",
          "type": "varchar(100)",
          "primaryKey": false,
          "notNull": true
        },
        "nameFr": {
          "name": "nameFr",
          "type": "varchar(100)",
          "primaryKey": false,
          "notNull": true
        },
        "descriptionEn": {
          "name": "descriptionEn",
          "type": "text",
          "primaryKey": false,
          "notNull": true
        },
        "descriptionFr": {
          "name": "descriptionFr",
          "type": "text",
          "primaryKey": false,
          "notNull": true
        },
        "syntax": {
          "name": "syntax",
          "type": "varchar(500)",
          "primaryKey": false,
          "notNull": true
        },
        "optionsEn": {
          "name": "optionsEn",
          "type": "text",
          "primaryKey": false,
          "notNull": false
        },
        "optionsFr": {
          "name": "optionsFr",
          "type": "text",
          "primaryKey": false,
          "notNull": false
        },
        "examplesEn": {
          "name": "examplesEn",
          "type": "text",
          "primaryKey": false,
          "notNull": false
        },
        "examplesFr": {
          "name": "examplesFr",
          "type": "text",
          "primaryKey": false,
          "notNull": false
        },
        "outputExample": {
          "name": "outputExample",
          "type": "text",
          "primaryKey": false,
          "notNull": false
        },
        "relatedCommands": {
          "name": "relatedCommands",
          "type": "json",
          "primaryKey": false,
          "notNull": false
        },
        "chapterId": {
          "name": "chapterId",
          "type": "integer",
          "primaryKey": false,
          "notNull": true
        },
        "difficulty": {
          "name": "difficulty",
          "type": "difficulty",
          "typeSchema": "public",
          "primaryKey": false,
          "notNull": true
        },
        "order": {
          "name": "order",
          "type": "integer",
          "primaryKey": false,
          "notNull": true
        },
        "createdAt": {
          "name": "createdAt",
          "type": "timestamp",
          "primaryKey": false,
          "notNull": true,
          "default": "now()"
        },
        "updatedAt": {
          "name": "updatedAt",
          "type": "timestamp",
          "primaryKey": false,
          "notNull": true,
          "default": "now()"
        }
      },
      "indexes": {},
      "foreignKeys": {},
      "compositePrimaryKeys": {},
      "uniqueConstraints": {},
      "policies": {},
      "checkConstraints": {},
      "isRLSEnabled": false
    },
    "public.examQuestions": {
      "name": "examQuestions",
      "schema": "",
      "columns": {
        "id": {
          "name": "id",
          "type": "integer",
          "primaryKey": true,
          "notNull": true,
          "identity": {
            "type": "byDefault",
            "name": "examQuestions_id_seq",
            "schema": "public",
            "increment": "1",
            "startWith": "1",
            "minValue": "1",
            "maxValue": "2147483647",
            "cache": "1",
            "cycle": false
          }
        },
        "examId": {
          "name": "examId",
          "type": "integer",
          "primaryKey": false,
          "notNull": true
        },
        "questionEn": {
          "name": "questionEn",
          "type": "text",
          "primaryKey": false,
          "notNull": true
        },
        "questionFr": {
          "name": "questionFr",
          "type": "text",
          "primaryKey": false,
          "notNull": true
        },
        "optionsEn": {
          "name": "optionsEn",
          "type": "json",
          "primaryKey": false,
          "notNull": true
        },
        "optionsFr": {
          "name": "optionsFr",
          "type": "json",
          "primaryKey": false,
          "notNull": true
        },
        "correctAnswer": {
          "name": "correctAnswer",
          "type": "varchar(10)",
          "primaryKey": false,
          "notNull": true
        },
        "explanationEn": {
          "name": "explanationEn",
          "type": "text",
          "primaryKey": false,
          "notNull": false
        },
        "explanationFr": {
          "name": "explanationFr",
          "type": "text",
          "primaryKey": false,
          "notNull": false
        },
        "difficulty": {
          "name": "difficulty",
          "type": "difficulty",
          "typeSchema": "public",
          "primaryKey": false,
          "notNull": true
        },
        "order": {
          "name": "order",
          "type": "integer",
          "primaryKey": false,
          "notNull": true
        },
        "createdAt": {
          "name": "createdAt",
          "type": "timestamp",
          "primaryKey": false,
          "notNull": true,
          "default": "now()"
        },
        "updatedAt": {
          "name": "updatedAt",
          "type": "timestamp",
          "primaryKey": false,
          "notNull": true,
          "default": "now()"
        }
      },
      "indexes": {},
      "foreignKeys": {},
      "compositePrimaryKeys": {},
      "uniqueConstraints": {},
      "policies": {},
      "checkConstraints": {},
      "isRLSEnabled": false
    },
    "public.examResults": {
      "name": "examResults",
      "schema": "",
      "columns": {
        "id": {
          "name": "id",
          "type": "integer",
          "primaryKey": true,
          "notNull": true,
          "identity": {
            "type": "byDefault",
            "name": "examResults_id_seq",
            "schema": "public",
            "increment": "1",
            "startWith": "1",
            "minValue": "1",
            "maxValue": "2147483647",
            "cache": "1",
            "cycle": false
          }
        },
        "userId": {
          "name": "userId",
          "type": "integer",
          "primaryKey": false,
          "notNull": true
        },
        "examId": {
          "name": "examId",
          "type": "integer",
          "primaryKey": false,
          "notNull": true
        },
        "score": {
          "name": "score",
          "type": "numeric(5, 2)",
          "primaryKey": false,
          "notNull": true
        },
        "passed": {
          "name": "passed",
          "type": "boolean",
          "primaryKey": false,
          "notNull": true
        },
        "completedAt": {
          "name": "completedAt",
          "type": "timestamp",
          "primaryKey": false,
          "notNull": true,
          "default": "now()"
        }
      },
      "indexes": {},
      "foreignKeys": {},
      "compositePrimaryKeys": {},
      "uniqueConstraints": {},
      "policies": {},
      "checkConstraints": {},
      "isRLSEnabled": false
    },
    "public.exams": {
      "name": "exams",
      "schema": "",
      "columns": {
        "id": {
          "name": "id",
          "type": "integer",
          "primaryKey": true,
          "notNull": true,
          "identity": {
            "type": "byDefault",
            "name": "exams_id_seq",
            "schema": "public",
            "increment": "1",
            "startWith": "1",
            "minValue": "1",
            "maxValue": "2147483647",
            "cache": "1",
            "cycle": false
          }
        },
        "titleEn": {
          "name": "titleEn",
          "type": "varchar(255)",
          "primaryKey": false,
          "notNull": true
        },
        "titleFr": {
          "name": "titleFr",
          "type": "varchar(255)",
          "primaryKey": false,
          "notNull": true
        },
        "descriptionEn": {
          "name": "descriptionEn",
          "type": "text",
          "primaryKey": false,
          "notNull": false
        },
        "descriptionFr": {
          "name": "descriptionFr",
          "type": "text",
          "primaryKey": false,
          "notNull": false
        },
        "timeLimit": {
          "name": "timeLimit",
          "type": "integer",
          "primaryKey": false,
          "notNull": true
        },
        "totalQuestions": {
          "name": "totalQuestions",
          "type": "integer",
          "primaryKey": false,
          "notNull": true
        },
        "passingScore": {
          "name": "passingScore",
          "type": "numeric(5, 2)",
          "primaryKey": false,
          "notNull": true
        },
        "order": {
          "name": "order",
          "type": "integer",
          "primaryKey": false,
          "notNull": true
        },
        "createdAt": {
          "name": "createdAt",
          "type": "timestamp",
          "primaryKey": false,
          "notNull": true,
          "default": "now()"
        },
        "updatedAt": {
          "name": "updatedAt",
          "type": "timestamp",
          "primaryKey": false,
          "notNull": true,
          "default": "now()"
        }
      },
      "indexes": {},
      "foreignKeys": {},
      "compositePrimaryKeys": {},
      "uniqueConstraints": {},
      "policies": {},
      "checkConstraints": {},
      "isRLSEnabled": false
    },
    "public.labProgress": {
      "name": "labProgress",
      "schema": "",
      "columns": {
        "id": {
          "name": "id",
          "type": "integer",
          "primaryKey": true,
          "notNull": true,
          "identity": {
            "type": "byDefault",
            "name": "labProgress_id_seq",
            "schema": "public",
            "increment": "1",
            "startWith": "1",
            "minValue": "1",
            "maxValue": "2147483647",
            "cache": "1",
            "cycle": false
          }
        },
        "userId": {
          "name": "userId",
          "type": "integer",
          "primaryKey": false,
          "notNull": true
        },
        "labId": {
          "name": "labId",
          "type": "integer",
          "primaryKey": false,
          "notNull": true
        },
        "completedAt": {
          "name": "completedAt",
          "type": "timestamp",
          "primaryKey": false,
          "notNull": false
        },
        "createdAt": {
          "name": "createdAt",
          "type": "timestamp",
          "primaryKey": false,
          "notNull": true,
          "default": "now()"
        }
      },
      "indexes": {},
      "foreignKeys": {},
      "compositePrimaryKeys": {},
      "uniqueConstraints": {},
      "policies": {},
      "checkConstraints": {},
      "isRLSEnabled": false
    },
    "public.labs": {
      "name": "labs",
      "schema": "",
      "columns": {
        "id": {
          "name": "id",
          "type": "integer",
          "primaryKey": true,
          "notNull": true,
          "identity": {
            "type": "byDefault",
            "name": "labs_id_seq",
            "schema": "public",
            "increment": "1",
            "startWith": "1",
            "minValue": "1",
            "maxValue": "2147483647",
            "cache": "1",
            "cycle": false
          }
        },
        "titleEn": {
          "name": "titleEn",
          "type": "varchar(255)",
          "primaryKey": false,
          "notNull": true
        },
        "titleFr": {
          "name": "titleFr",
          "type": "varchar(255)",
          "primaryKey": false,
          "notNull": true
        },
        "descriptionEn": {
          "name": "descriptionEn",
          "type": "text",
          "primaryKey": false,
          "notNull": false
        },
        "descriptionFr": {
          "name": "descriptionFr",
          "type": "text",
          "primaryKey": false,
          "notNull": false
        },
        "difficulty": {
          "name": "difficulty",
          "type": "difficulty",
          "typeSchema": "public",
          "primaryKey": false,
          "notNull": true
        },
        "estimatedDuration": {
          "name": "estimatedDuration",
          "type": "integer",
          "primaryKey": false,
          "notNull": false
        },
        "objectivesEn": {
          "name": "objectivesEn",
          "type": "text",
          "primaryKey": false,
          "notNull": false
        },
        "objectivesFr": {
          "name": "objectivesFr",
          "type": "text",
          "primaryKey": false,
          "notNull": false
        },
        "prerequisitesEn": {
          "name": "prerequisitesEn",
          "type": "text",
          "primaryKey": false,
          "notNull": false
        },
        "prerequisitesFr": {
          "name": "prerequisitesFr",
          "type": "text",
          "primaryKey": false,
          "notNull": false
        },
        "instructionsEn": {
          "name": "instructionsEn",
          "type": "text",
          "primaryKey": false,
          "notNull": false
        },
        "instructionsFr": {
          "name": "instructionsFr",
          "type": "text",
          "primaryKey": false,
          "notNull": false
        },
        "validationEn": {
          "name": "validationEn",
          "type": "text",
          "primaryKey": false,
          "notNull": false
        },
        "validationFr": {
          "name": "validationFr",
          "type": "text",
          "primaryKey": false,
          "notNull": false
        },
        "solutionEn": {
          "name": "solutionEn",
          "type": "text",
          "primaryKey": false,
          "notNull": false
        },
        "solutionFr": {
          "name": "solutionFr",
          "type": "text",
          "primaryKey": false,
          "notNull": false
        },
        "chapterId": {
          "name": "chapterId",
          "type": "integer",
          "primaryKey": false,
          "notNull": false
        },
        "order": {
          "name": "order",
          "type": "integer",
          "primaryKey": false,
          "notNull": true
        },
        "createdAt": {
          "name": "createdAt",
          "type": "timestamp",
          "primaryKey": false,
          "notNull": true,
          "default": "now()"
        },
        "updatedAt": {
          "name": "updatedAt",
          "type": "timestamp",
          "primaryKey": false,
          "notNull": true,
          "default": "now()"
        }
      },
      "indexes": {},
      "foreignKeys": {},
      "compositePrimaryKeys": {},
      "uniqueConstraints": {},
      "policies": {},
      "checkConstraints": {},
      "isRLSEnabled": false
    },
    "public.userProgress": {
      "name": "userProgress",
      "schema": "",
      "columns": {
        "id": {
          "name": "id",
          "type": "integer",
          "primaryKey": true,
          "notNull": true,
          "identity": {
            "type": "byDefault",
            "name": "userProgress_id_seq",
            "schema": "public",
            "increment": "1",
            "startWith": "1",
            "minValue": "1",
            "maxValue": "2147483647",
            "cache": "1",
            "cycle": false
          }
        },
        "userId": {
          "name": "userId",
          "type": "integer",
          "primaryKey": false,
          "notNull": true
        },
        "chapterId": {
          "name": "chapterId",
          "type": "integer",
          "primaryKey": false,
          "notNull": true
        },
        "completedAt": {
          "name": "completedAt",
          "type": "timestamp",
          "primaryKey": false,
          "notNull": false
        },
        "progress": {
          "name": "progress",
          "type": "numeric(5, 2)",
          "primaryKey": false,
          "notNull": false,
          "default": "'0'"
        },
        "createdAt": {
          "name": "createdAt",
          "type": "timestamp",
          "primaryKey": false,
          "notNull": true,
          "default": "now()"
        },
        "updatedAt": {
          "name": "updatedAt",
          "type": "timestamp",
          "primaryKey": false,
          "notNull": true,
          "default": "now()"
        }
      },
      "indexes": {},
      "foreignKeys": {},
      "compositePrimaryKeys": {},
      "uniqueConstraints": {},
      "policies": {},
      "checkConstraints": {},
      "isRLSEnabled": false
    },
    "public.users": {
      "name": "users",
      "schema": "",
      "columns": {
        "id": {
          "name": "id",
          "type": "integer",
          "primaryKey": true,
          "notNull": true,
          "identity": {
            "type": "byDefault",
            "name": "users_id_seq",
            "schema": "public",
            "increment": "1",
            "startWith": "1",
            "minValue": "1",
            "maxValue": "2147483647",
            "cache": "1",
            "cycle": false
          }
        },
        "openId": {
          "name": "openId",
          "type": "varchar(64)",
          "primaryKey": false,
          "notNull": true
        },
        "name": {
          "name": "name",
          "type": "text",
          "primaryKey": false,
          "notNull": false
        },
        "email": {
          "name": "email",
          "type": "varchar(320)",
          "primaryKey": false,
          "notNull": false
        },
        "loginMethod": {
          "name": "loginMethod",
          "type": "varchar(64)",
          "primaryKey": false,
          "notNull": false
        },
        "role": {
          "name": "role",
          "type": "role",
          "typeSchema": "public",
          "primaryKey": false,
          "notNull": true,
          "default": "'user'"
        },
        "language": {
          "name": "language",
          "type": "varchar(5)",
          "primaryKey": false,
          "notNull": true,
          "default": "'en'"
        },
        "theme": {
          "name": "theme",
          "type": "varchar(10)",
          "primaryKey": false,
          "notNull": true,
          "default": "'light'"
        },
        "createdAt": {
          "name": "createdAt",
          "type": "timestamp",
          "primaryKey": false,
          "notNull": true,
          "default": "now()"
        },
        "updatedAt": {
          "name": "updatedAt",
          "type": "timestamp",
          "primaryKey": false,
          "notNull": true,
          "default": "now()"
        },
        "lastSignedIn": {
          "name": "lastSignedIn",
          "type": "timestamp",
          "primaryKey": false,
          "notNull": true,
          "default": "now()"
        }
      },
      "indexes": {},
      "foreignKeys": {},
      "compositePrimaryKeys": {},
      "uniqueConstraints": {
        "users_openId_unique": {
          "name": "users_openId_unique",
          "nullsNotDistinct": false,
          "columns": ["openId"]
        }
      },
      "policies": {},
      "checkConstraints": {},
      "isRLSEnabled": false
    }
  },
  "enums": {
    "public.difficulty": {
      "name": "difficulty",
      "schema": "public",
      "values": [
        "beginner",
        "intermediate",
        "advanced",
        "easy",
        "medium",
        "hard"
      ]
    },
    "public.role": {
      "name": "role",
      "schema": "public",
      "values": ["user", "admin"]
    }
  },
  "schemas": {},
  "sequences": {},
  "roles": {},
  "policies": {},
  "views": {},
  "_meta": {
    "columns": {},
    "schemas": {},
    "tables": {}
  }
}
